{"nodes":[{"bias":0,"type":"input","squash":"LOGISTIC","mask":1,"index":0},{"bias":0,"type":"input","squash":"LOGISTIC","mask":1,"index":1},{"bias":0,"type":"input","squash":"LOGISTIC","mask":1,"index":2},{"bias":0,"type":"input","squash":"LOGISTIC","mask":1,"index":3},{"bias":0,"type":"input","squash":"LOGISTIC","mask":1,"index":4},{"bias":0,"type":"input","squash":"LOGISTIC","mask":1,"index":5},{"bias":0,"type":"input","squash":"LOGISTIC","mask":1,"index":6},{"bias":0,"type":"input","squash":"LOGISTIC","mask":1,"index":7},{"bias":0.03526219722175089,"type":"output","squash":"LOGISTIC","mask":1,"index":8},{"bias":0.016453291711846327,"type":"output","squash":"LOGISTIC","mask":1,"index":9},{"bias":-0.05089677347670621,"type":"output","squash":"LOGISTIC","mask":1,"index":10},{"bias":0.034833716515744406,"type":"output","squash":"LOGISTIC","mask":1,"index":11}],"connections":[{"weight":1.4431403584358966,"from":0,"to":8,"gater":null},{"weight":0.26696033170085265,"from":0,"to":9,"gater":null},{"weight":1.1930781855950503,"from":0,"to":10,"gater":null},{"weight":2.359944401698262,"from":0,"to":11,"gater":null},{"weight":1.2406763992888745,"from":1,"to":8,"gater":null},{"weight":3.1933450945763413,"from":1,"to":9,"gater":null},{"weight":0.9170082822077861,"from":1,"to":10,"gater":null},{"weight":2.0960568661584436,"from":1,"to":11,"gater":null},{"weight":0.18878089461982395,"from":2,"to":8,"gater":null},{"weight":0.9533378046102312,"from":2,"to":9,"gater":null},{"weight":1.6181131775812485,"from":2,"to":10,"gater":null},{"weight":0.08755317995750644,"from":2,"to":11,"gater":null},{"weight":0.11748580177623591,"from":3,"to":8,"gater":null},{"weight":2.6201655306164904,"from":3,"to":9,"gater":null},{"weight":1.1375315606685303,"from":3,"to":10,"gater":null},{"weight":2.613511072927195,"from":3,"to":11,"gater":null},{"weight":2.424095904052881,"from":4,"to":8,"gater":null},{"weight":2.778132085048009,"from":4,"to":9,"gater":null},{"weight":3.394469630608355,"from":4,"to":10,"gater":null},{"weight":0.26257796632344377,"from":4,"to":11,"gater":null},{"weight":1.259786195261814,"from":5,"to":8,"gater":null},{"weight":0.6768083310517872,"from":5,"to":9,"gater":null},{"weight":3.1560778187001874,"from":5,"to":10,"gater":null},{"weight":0.05153341315034332,"from":5,"to":11,"gater":null},{"weight":3.2920711514040066,"from":6,"to":8,"gater":null},{"weight":3.3582707243797074,"from":6,"to":9,"gater":null},{"weight":2.2739580573967704,"from":6,"to":10,"gater":null},{"weight":0.7561504885256278,"from":6,"to":11,"gater":null},{"weight":3.857061457720979,"from":7,"to":8,"gater":null},{"weight":2.520863155669118,"from":7,"to":9,"gater":null},{"weight":2.472766878037085,"from":7,"to":10,"gater":null},{"weight":1.9849617437208975,"from":7,"to":11,"gater":null}],"input":8,"output":4,"dropout":0}